pyioping/__init__.py
pyioping-0.1.dist-info/LICENSE
pyioping-0.1.dist-info/METADATA
pyioping-0.1.dist-info/WHEEL
pyioping-0.1.dist-info/top_level.txt
pyioping-0.1.dist-info/RECORD
