Metadata-Version: 2.1
Name: pyioping
Version: 0.1
Summary: Abstraction layer for ioping linux binary
Home-page: https://github.com/jinjamator/pyioping
Author: Wilhelm Putz
Author-email: wp@aci.guru
License: ASL V2
Classifier: License :: OSI Approved :: Apache Software License
Classifier: Programming Language :: Python :: 3.7
Classifier: Programming Language :: Python :: 3.8
Classifier: Topic :: System :: Installation/Setup
Classifier: Topic :: System :: Systems Administration
Classifier: Topic :: Utilities
Requires-Python: >=3.7
License-File: LICENSE
